entry_points_txt/__init__.py
entry_points_txt/py.typed
entry_points_txt-0.2.1.dist-info/METADATA
entry_points_txt-0.2.1.dist-info/WHEEL
entry_points_txt-0.2.1.dist-info/licenses/LICENSE
entry_points_txt-0.2.1.dist-info/RECORD
