Metadata-Version: 2.3
Name: entry-points-txt
Version: 0.2.1
Summary: Read & write entry_points.txt files
Project-URL: Source Code, https://github.com/wheelodex/entry-points-txt
Project-URL: Bug Tracker, https://github.com/wheelodex/entry-points-txt/issues
Author-email: John Thorvald Wodder II <entry-points-txt@varonathe.org>
License: MIT
Keywords: entry points,entry_points.txt
Classifier: License :: OSI Approved :: MIT License
Classifier: Programming Language :: Python :: 3
Classifier: Programming Language :: Python :: 3 :: Only
Classifier: Programming Language :: Python :: 3.8
Classifier: Programming Language :: Python :: 3.9
Classifier: Programming Language :: Python :: 3.10
Classifier: Programming Language :: Python :: 3.11
Classifier: Programming Language :: Python :: 3.12
Classifier: Programming Language :: Python :: 3.13
Classifier: Programming Language :: Python :: Implementation :: CPython
Classifier: Programming Language :: Python :: Implementation :: PyPy
Classifier: Topic :: Software Development :: Libraries :: Python Modules
Classifier: Topic :: Text Processing
Classifier: Typing :: Typed
Requires-Python: >=3.8
